LICENSE.txt
MANIFEST.in
Makefile
README.rst
requirements.txt
setup.cfg
setup.py
cwmud/__init__.py
cwmud/__main__.py
cwmud/nanny.py
cwmud/settings.py
cwmud.egg-info/PKG-INFO
cwmud.egg-info/SOURCES.txt
cwmud.egg-info/dependency_links.txt
cwmud.egg-info/not-zip-safe
cwmud.egg-info/requires.txt
cwmud.egg-info/top_level.txt
cwmud/contrib/__init__.py
cwmud/contrib/weather/__init__.py
cwmud/contrib/weather/patterns.py
cwmud/contrib/worldgen/__init__.py
cwmud/contrib/worldgen/maps.py
cwmud/contrib/worldgen/terrain.py
cwmud/core/__init__.py
cwmud/core/accounts.py
cwmud/core/attributes.py
cwmud/core/channels.py
cwmud/core/characters.py
cwmud/core/cli.py
cwmud/core/clients.py
cwmud/core/commands.py
cwmud/core/const.py
cwmud/core/entities.py
cwmud/core/events.py
cwmud/core/items.py
cwmud/core/json.py
cwmud/core/logs.py
cwmud/core/menus.py
cwmud/core/messages.py
cwmud/core/npcs.py
cwmud/core/pickle.py
cwmud/core/players.py
cwmud/core/random.py
cwmud/core/requests.py
cwmud/core/server.py
cwmud/core/sessions.py
cwmud/core/shells.py
cwmud/core/storage.py
cwmud/core/text.py
cwmud/core/timing.py
cwmud/core/world.py
cwmud/core/cmds/__init__.py
cwmud/core/cmds/cmd_admin.py
cwmud/core/cmds/cmd_basic.py
cwmud/core/cmds/cmd_comm.py
cwmud/core/cmds/cmd_info.py
cwmud/core/cmds/cmd_move.py
cwmud/core/cmds/cmd_olc.py
cwmud/core/protocols/__init__.py
cwmud/core/protocols/telnet.py
cwmud/core/protocols/websockets.py
cwmud/core/utils/__init__.py
cwmud/core/utils/decorators.py
cwmud/core/utils/exceptions.py
cwmud/core/utils/funcs.py
cwmud/core/utils/mixins.py
cwmud/game/__init__.py
cwmud/libs/__init__.py
cwmud/libs/miniboa.LICENSE.TXT
cwmud/libs/miniboa.py
docs/.gitignore
docs/Makefile
docs/conf.py
docs/index.rst
docs/make.bat
docs/requirements.txt
tests/conftest.py
tests/requirements.txt
tests/test_meta.py
tests/test_nanny.py
tests/core/test_accounts.py
tests/core/test_characters.py
tests/core/test_commands.py
tests/core/test_entities.py
tests/core/test_events.py
tests/core/test_json.py
tests/core/test_logs.py
tests/core/test_menus.py
tests/core/test_pickle.py
tests/core/test_players.py
tests/core/test_requests.py
tests/core/test_server.py
