Metadata-Version: 1.1
Name: cwmud
Version: 0.4.0
Summary: Clockwork MUD server
Home-page: https://github.com/whutch/cwmud
Author: Will Hutcheson
Author-email: will@whutch.com
License: MIT
Keywords: clockwork,mud,mux,moo,mush
Platform: UNKNOWN
Classifier: Development Status :: 3 - Alpha
Classifier: Environment :: Console
Classifier: Intended Audience :: Developers
Classifier: License :: OSI Approved :: MIT License
Classifier: Natural Language :: English
Classifier: Operating System :: OS Independent
Classifier: Programming Language :: Python
Classifier: Programming Language :: Python :: 3.4
Classifier: Topic :: Games/Entertainment :: Multi-User Dungeons (MUD)
Classifier: Topic :: Software Development :: Libraries :: Python Modules
